<?xml version="1.0" encoding="UTF-8"?>
<!DOCTYPE hibernate-mapping PUBLIC "-//Hibernate/Hibernate Mapping DTD 3.0//EN" "http://hibernate.sourceforge.net/hibernate-mapping-3.0.dtd" >
<hibernate-mapping>

<class name="com.smit.vo.SmitRegisteredPushServiceId" table="SmitRegisteredPushServiceId">
 <id name="id">
 <generator class="native"></generator>
 </id>
 <property name="pushServiceID" column="pushServiceID"/>
 <property name="serviceType" column="serviceType"/>
 <property name="userName" column="userName"/>
 <property name="userAccount" column="userAccount"/>
</class>
</hibernate-mapping>
